openmapflow/Dockerfile
openmapflow/__init__.py
openmapflow/bands.py
openmapflow/bbox.py
openmapflow/config.py
openmapflow/constants.py
openmapflow/datasets.py
openmapflow/ee_boundingbox.py
openmapflow/ee_exporter.py
openmapflow/engineer.py
openmapflow/generate.py
openmapflow/inference.py
openmapflow/inference_utils.py
openmapflow/inference_widgets.py
openmapflow/label_utils.py
openmapflow/labeled_dataset.py
openmapflow/pytorch_dataset.py
openmapflow/torchserve_handler.py
openmapflow/train_utils.py
openmapflow/utils.py
openmapflow/eo/__init__.py
openmapflow/eo/era5.py
openmapflow/eo/sentinel1.py
openmapflow/eo/sentinel2.py
openmapflow/eo/srtm.py
openmapflow/notebooks/compare_ceo_labels.ipynb
openmapflow/notebooks/create_map.ipynb
openmapflow/notebooks/generate_project.ipynb
openmapflow/notebooks/new_data.ipynb
openmapflow/notebooks/train.ipynb
openmapflow/notebooks/tutorial.ipynb
openmapflow/scripts/deploy.sh
openmapflow/scripts/merging.sh
openmapflow/scripts/openmapflow
openmapflow/scripts/torchserve_start.sh
openmapflow/templates/README.md
openmapflow/templates/datasets.py
openmapflow/templates/evaluate.py
openmapflow/templates/github-deploy.yaml
openmapflow/templates/github-test.yaml
openmapflow/templates/integration_test_datasets.py
openmapflow/templates/integration_test_project.py
openmapflow/templates/integration_test_train_evaluate.py
openmapflow/templates/openmapflow-default.yaml
openmapflow/templates/requirements.txt
openmapflow/templates/train.py
openmapflow/trigger_inference_function/main.py
openmapflow/trigger_inference_function/requirements.txt
openmapflow-0.2.4.data/scripts/deploy.sh
openmapflow-0.2.4.data/scripts/openmapflow
openmapflow-0.2.4.dist-info/LICENSE
openmapflow-0.2.4.dist-info/METADATA
openmapflow-0.2.4.dist-info/WHEEL
openmapflow-0.2.4.dist-info/top_level.txt
openmapflow-0.2.4.dist-info/RECORD
