Metadata-Version: 2.1
Name: openmapflow
Version: 0.2.4
Summary: Creating maps with machine learning models and earth observation data.
Home-page: https://github.com/nasaharvest/openmapflow
Author: Ivan Zvonkov
Author-email: izvonkov@umd.edu
License: Apache License 2.0
Classifier: Programming Language :: Python :: 3
Classifier: License :: OSI Approved :: Apache Software License
Classifier: Operating System :: OS Independent
Requires-Python: >=3.6
License-File: LICENSE
Requires-Dist: numpy
Requires-Dist: pandas <2,>=1.3.5
Requires-Dist: pyyaml >=6.0
Requires-Dist: requests
Requires-Dist: tqdm >=4.9.0
Provides-Extra: all
Requires-Dist: cmocean ; extra == 'all'
Requires-Dist: earthengine-api ; extra == 'all'
Requires-Dist: geopandas ; extra == 'all'
Requires-Dist: google-cloud-storage ; extra == 'all'
Requires-Dist: ipython ; extra == 'all'
Requires-Dist: netCDF4 ; extra == 'all'
Requires-Dist: rasterio ; extra == 'all'
Requires-Dist: xarray ==0.19 ; extra == 'all'
Requires-Dist: fastcore <1.5.18 ; extra == 'all'
Requires-Dist: tsai ; extra == 'all'
Provides-Extra: data
Requires-Dist: cmocean ; extra == 'data'
Requires-Dist: earthengine-api ; extra == 'data'
Requires-Dist: geopandas ; extra == 'data'
Requires-Dist: google-cloud-storage ; extra == 'data'
Requires-Dist: netCDF4 ; extra == 'data'
Requires-Dist: rasterio ; extra == 'data'
Requires-Dist: xarray ==0.19 ; extra == 'data'
